Microfire_Mod_EC/Microfire_Mod_EC.py
Microfire_Mod_EC/__init__.py
Microfire_Mod_EC/shell - Copy.py
Microfire_Mod_EC/shell.py
microfire_mod_ec-0.9.0.dist-info/METADATA
microfire_mod_ec-0.9.0.dist-info/WHEEL
microfire_mod_ec-0.9.0.dist-info/licenses/LICENSE
microfire_mod_ec-0.9.0.dist-info/RECORD
