Metadata-Version: 2.1
Name: Microfire_Mod_EC
Version: 0.9.0
Summary: Add the ability to measure EC to your hardware application with a fully digital interface.
Project-URL: Homepage, https://microfire.co
Project-URL: Bug Tracker, https://github.com/u-fire/Mod-EC/issues
Author-email: Microfire LLC <contact@microfire.co>
License-File: LICENSE
Classifier: License :: OSI Approved :: MIT License
Classifier: Operating System :: OS Independent
Classifier: Programming Language :: Python :: 3
Requires-Python: >=3.6
